alfaci/__init__.py
alfaci/cli.py
alfaci/env.py
alfaci/repo.py
alfaci/version.py
alfaci/envs/__init__.py
alfaci/envs/fairroot.py
alfa_ci-0.1.0.dist-info/LICENSE
alfa_ci-0.1.0.dist-info/METADATA
alfa_ci-0.1.0.dist-info/WHEEL
alfa_ci-0.1.0.dist-info/entry_points.txt
alfa_ci-0.1.0.dist-info/top_level.txt
alfa_ci-0.1.0.dist-info/RECORD
