Metadata-Version: 2.1
Name: alfa-ci
Version: 0.1.0
Summary: alfa-ci environment manager
Home-page: https://github.com/FairRootGroup/alfa-ci
Author: Dennis Klein
Author-email: d.klein@gsi.de
License: GPLv3+
Platform: UNKNOWN
Classifier: Programming Language :: Python :: 3
Classifier: License :: OSI Approved :: GNU General Public License v3 or later (GPLv3+)
Requires-Python: >=3.6
Requires-Dist: argcomplete
Requires-Dist: pyyaml
